pynormalizenumexp/__init__.py
pynormalizenumexp/expression/__init__.py
pynormalizenumexp/expression/abstime.py
pynormalizenumexp/expression/base.py
pynormalizenumexp/expression/duration.py
pynormalizenumexp/expression/numerical.py
pynormalizenumexp/expression/reltime.py
pynormalizenumexp/normalize_numexp.py
pynormalizenumexp/normalizer/__init__.py
pynormalizenumexp/normalizer/abstime_expr_normalizer.py
pynormalizenumexp/normalizer/base.py
pynormalizenumexp/normalizer/converter/__init__.py
pynormalizenumexp/normalizer/converter/japanese_number_converter.py
pynormalizenumexp/normalizer/converter/number_converter.py
pynormalizenumexp/normalizer/duration_expr_normalizer.py
pynormalizenumexp/normalizer/inappropriate_expr_remover.py
pynormalizenumexp/normalizer/number_extractor.py
pynormalizenumexp/normalizer/number_normalizer.py
pynormalizenumexp/normalizer/numerical_expr_normalizer.py
pynormalizenumexp/normalizer/reltime_expr_normalizer.py
pynormalizenumexp/normalizer/symbol_fixer.py
pynormalizenumexp/py.typed
pynormalizenumexp/resources/__init__.py
pynormalizenumexp/resources/dict/README.md
pynormalizenumexp/resources/dict/__init__.py
pynormalizenumexp/resources/dict/ja/__init__.py
pynormalizenumexp/resources/dict/ja/abstime_expression.json
pynormalizenumexp/resources/dict/ja/abstime_prefix.json
pynormalizenumexp/resources/dict/ja/abstime_prefix_counter.json
pynormalizenumexp/resources/dict/ja/abstime_suffix.json
pynormalizenumexp/resources/dict/ja/chinese_character.json
pynormalizenumexp/resources/dict/ja/duration_expression.json
pynormalizenumexp/resources/dict/ja/duration_prefix.json
pynormalizenumexp/resources/dict/ja/duration_prefix_counter.json
pynormalizenumexp/resources/dict/ja/duration_suffix.json
pynormalizenumexp/resources/dict/ja/inappropriate_strings.json
pynormalizenumexp/resources/dict/ja/num_counter.json
pynormalizenumexp/resources/dict/ja/num_prefix.json
pynormalizenumexp/resources/dict/ja/num_prefix_counter.json
pynormalizenumexp-0.3.4.dist-info/LICENSE
pynormalizenumexp-0.3.4.dist-info/METADATA
pynormalizenumexp-0.3.4.dist-info/WHEEL
pynormalizenumexp-0.3.4.dist-info/RECORD
