Metadata-Version: 2.1
Name: pynormalizenumexp
Version: 0.3.4
Summary: NormalizeNumExp for Python
Home-page: https://github.com/tkscode/pyNormalizeNumExp
License: BSD 3-Clause
Keywords: Python,NLP,NormalizeNumExp
Author: tkscode
Requires-Python: >=3.9,<4.0
Classifier: License :: Other/Proprietary License
Classifier: Programming Language :: Python :: 3
Classifier: Programming Language :: Python :: 3.9
Classifier: Programming Language :: Python :: 3.10
Classifier: Programming Language :: Python :: 3.11
Classifier: Programming Language :: Python :: 3.12
Project-URL: Repository, https://github.com/tkscode/pyNormalizeNumExp
